{
  "version": "1.0.0",
  "rss": "<LINK TO RSS FEED>",
  "discord": {
    "clientId": "<FILL IN OR REMOVE DISCORD OBJECT>",
    "smallImageText": "<FILL IN OR REMOVE DISCORD OBJECT>",
    "smallImageKey": "<FILL IN OR REMOVE DISCORD OBJECT>"
  },
  "servers": [
    {
      "id": "루나타운-1.20.1",
      "name": "루나타운 (Minecraft 1.20.1)",
      "description": "루나타운 Running Minecraft 1.20.1 (Forge v47.3.22)",
      "icon": "https://cdn.discordapp.com/attachments/1286656355138011209/1324314188998377512/pack.png?ex=67897f73&is=67882df3&hm=ad97053e5a2a500a90afdc9c20572c216675e9c55a9372f4566607649f0e59ed&",
      "version": "1.0.0",
      "address": "211.53.196.214:25565",
      "minecraftVersion": "1.20.1",
      "discord": {
        "shortId": "<FILL IN OR REMOVE DISCORD OBJECT>",
        "largeImageText": "<FILL IN OR REMOVE DISCORD OBJECT>",
        "largeImageKey": "<FILL IN OR REMOVE DISCORD OBJECT>"
      },
      "mainServer": true,
      "autoconnect": true,
      "modules": [
        {
          "id": "net.minecraftforge:lowcodelanguage:1.20.1-47.3.22",
          "name": "Minecraft Forge (lowcodelanguage)",
          "type": "ForgeHosted",
          "classpath": true,
          "artifact": {
            "size": 7401,
            "MD5": "81dc6bb506829755e3d29fbaab4d9bbb",
            "url": "https://awe4859.github.io/moon_server_FTP/repo/lib/net/minecraftforge/lowcodelanguage/1.20.1-47.3.22/lowcodelanguage-1.20.1-47.3.22.jar"
          },
          "subModules": [
            {
              "id": "1.20.1-47.3.22",
              "name": "Minecraft Forge (version.json)",
              "type": "VersionManifest",
              "artifact": {
                "size": 16624,
                "MD5": "5b2f060ab24af9e927398b29135aa7c5",
                "url": "https://awe4859.github.io/moon_server_FTP/repo/versions/1.20.1-forge-47.3.22/1.20.1-forge-47.3.22.json"
              }
            },
            {
              "id": "net.minecraftforge:fmlcore:1.20.1-47.3.22",
              "name": "Minecraft Forge (fmlcore)",
              "type": "Library",
              "classpath": true,
              "artifact": {
                "size": 118579,
                "MD5": "e00b6331668c2b16cf6dc2fca5579157",
                "url": "https://awe4859.github.io/moon_server_FTP/repo/lib/net/minecraftforge/fmlcore/1.20.1-47.3.22/fmlcore-1.20.1-47.3.22.jar"
              },
              "subModules": []
            },
            {
              "id": "net.minecraftforge:javafmllanguage:1.20.1-47.3.22",
              "name": "Minecraft Forge (javafmllanguage)",
              "type": "Library",
              "classpath": true,
              "artifact": {
                "size": 16857,
                "MD5": "b73d7c55ab0a5af07629a27e8398d774",
                "url": "https://awe4859.github.io/moon_server_FTP/repo/lib/net/minecraftforge/javafmllanguage/1.20.1-47.3.22/javafmllanguage-1.20.1-47.3.22.jar"
              },
              "subModules": []
            },
            {
              "id": "net.minecraftforge:mclanguage:1.20.1-47.3.22",
              "name": "Minecraft Forge (mclanguage)",
              "type": "Library",
              "classpath": true,
              "artifact": {
                "size": 5001,
                "MD5": "8b86e5f5aabc03162edeaad6b241997d",
                "url": "https://awe4859.github.io/moon_server_FTP/repo/lib/net/minecraftforge/mclanguage/1.20.1-47.3.22/mclanguage-1.20.1-47.3.22.jar"
              },
              "subModules": []
            },
            {
              "id": "net.minecraftforge:forge:1.20.1-47.3.22:universal",
              "name": "Minecraft Forge (universal jar)",
              "type": "Library",
              "classpath": false,
              "artifact": {
                "size": 2761726,
                "MD5": "d11524d18b5274cc5d9de749d34f1e37",
                "url": "https://awe4859.github.io/moon_server_FTP/repo/lib/net/minecraftforge/forge/1.20.1-47.3.22/forge-1.20.1-47.3.22-universal.jar"
              },
              "subModules": []
            },
            {
              "id": "net.minecraftforge:forge:1.20.1-47.3.22:client",
              "name": "Minecraft Forge (client jar)",
              "type": "Library",
              "classpath": false,
              "artifact": {
                "size": 4794071,
                "MD5": "d13b796e89ac734128d8fa5b2d98de47",
                "url": "https://awe4859.github.io/moon_server_FTP/repo/lib/net/minecraftforge/forge/1.20.1-47.3.22/forge-1.20.1-47.3.22-client.jar"
              },
              "subModules": []
            },
            {
              "id": "net.minecraft:client:1.20.1-20230612.114412:srg",
              "name": "Minecraft Forge (client srg)",
              "type": "Library",
              "classpath": false,
              "artifact": {
                "size": 18842082,
                "MD5": "8bfacfba4f54cda741019756165c5ecf",
                "url": "https://awe4859.github.io/moon_server_FTP/repo/lib/net/minecraft/client/1.20.1-20230612.114412/client-1.20.1-20230612.114412-srg.jar"
              },
              "subModules": []
            },
            {
              "id": "net.minecraft:client:1.20.1-20230612.114412:slim",
              "name": "Minecraft Forge (client slim)",
              "type": "Library",
              "classpath": false,
              "artifact": {
                "size": 12592249,
                "MD5": "28edebec7b5a007bc9961ee9bab4d764",
                "url": "https://awe4859.github.io/moon_server_FTP/repo/lib/net/minecraft/client/1.20.1-20230612.114412/client-1.20.1-20230612.114412-slim.jar"
              },
              "subModules": []
            },
            {
              "id": "net.minecraft:client:1.20.1-20230612.114412:extra",
              "name": "Minecraft Forge (client extra)",
              "type": "Library",
              "classpath": false,
              "artifact": {
                "size": 10436626,
                "MD5": "da6bb1a2c23108392fd6c103da40867c",
                "url": "https://awe4859.github.io/moon_server_FTP/repo/lib/net/minecraft/client/1.20.1-20230612.114412/client-1.20.1-20230612.114412-extra.jar"
              },
              "subModules": []
            },
            {
              "id": "cpw.mods:securejarhandler:2.1.10",
              "name": "Minecraft Forge (securejarhandler)",
              "type": "Library",
              "artifact": {
                "size": 88749,
                "MD5": "d9ff48d1c68388270388b803fa42611e",
                "url": "https://awe4859.github.io/moon_server_FTP/repo/lib/cpw/mods/securejarhandler/2.1.10/securejarhandler-2.1.10.jar"
              }
            },
            {
              "id": "org.ow2.asm:asm:9.7.1",
              "name": "Minecraft Forge (asm)",
              "type": "Library",
              "artifact": {
                "size": 126093,
                "MD5": "e2cdd32d198ad31427d298eee9d39d8d",
                "url": "https://awe4859.github.io/moon_server_FTP/repo/lib/org/ow2/asm/asm/9.7.1/asm-9.7.1.jar"
              }
            },
            {
              "id": "org.ow2.asm:asm-commons:9.7.1",
              "name": "Minecraft Forge (asm-commons)",
              "type": "Library",
              "artifact": {
                "size": 73459,
                "MD5": "8344aea3c8b7d707e9d35a62710e77c9",
                "url": "https://awe4859.github.io/moon_server_FTP/repo/lib/org/ow2/asm/asm-commons/9.7.1/asm-commons-9.7.1.jar"
              }
            },
            {
              "id": "org.ow2.asm:asm-tree:9.7.1",
              "name": "Minecraft Forge (asm-tree)",
              "type": "Library",
              "artifact": {
                "size": 51939,
                "MD5": "e85029f613b6469989cc7cf53fe06b74",
                "url": "https://awe4859.github.io/moon_server_FTP/repo/lib/org/ow2/asm/asm-tree/9.7.1/asm-tree-9.7.1.jar"
              }
            },
            {
              "id": "org.ow2.asm:asm-util:9.7.1",
              "name": "Minecraft Forge (asm-util)",
              "type": "Library",
              "artifact": {
                "size": 94519,
                "MD5": "36d373a9cd6cad9b35db9f984c6b4bbb",
                "url": "https://awe4859.github.io/moon_server_FTP/repo/lib/org/ow2/asm/asm-util/9.7.1/asm-util-9.7.1.jar"
              }
            },
            {
              "id": "org.ow2.asm:asm-analysis:9.7.1",
              "name": "Minecraft Forge (asm-analysis)",
              "type": "Library",
              "artifact": {
                "size": 35126,
                "MD5": "4cd9e7178dfb85371bba3077e40cd514",
                "url": "https://awe4859.github.io/moon_server_FTP/repo/lib/org/ow2/asm/asm-analysis/9.7.1/asm-analysis-9.7.1.jar"
              }
            },
            {
              "id": "net.minecraftforge:accesstransformers:8.0.4",
              "name": "Minecraft Forge (accesstransformers)",
              "type": "Library",
              "artifact": {
                "size": 77756,
                "MD5": "f0d3533f9437ba4428eaee9f28f7ecd9",
                "url": "https://awe4859.github.io/moon_server_FTP/repo/lib/net/minecraftforge/accesstransformers/8.0.4/accesstransformers-8.0.4.jar"
              }
            },
            {
              "id": "org.antlr:antlr4-runtime:4.9.1",
              "name": "Minecraft Forge (antlr4-runtime)",
              "type": "Library",
              "artifact": {
                "size": 337868,
                "MD5": "0dcc4b860d5d8d2852ab94d58c56ca2d",
                "url": "https://awe4859.github.io/moon_server_FTP/repo/lib/org/antlr/antlr4-runtime/4.9.1/antlr4-runtime-4.9.1.jar"
              }
            },
            {
              "id": "net.minecraftforge:eventbus:6.0.5",
              "name": "Minecraft Forge (eventbus)",
              "type": "Library",
              "artifact": {
                "size": 53985,
                "MD5": "2a6245210b446b2144071e71ca13432b",
                "url": "https://awe4859.github.io/moon_server_FTP/repo/lib/net/minecraftforge/eventbus/6.0.5/eventbus-6.0.5.jar"
              }
            },
            {
              "id": "net.minecraftforge:forgespi:7.0.1",
              "name": "Minecraft Forge (forgespi)",
              "type": "Library",
              "artifact": {
                "size": 29831,
                "MD5": "bd34d20287dc95201fe9475a8bbc2540",
                "url": "https://awe4859.github.io/moon_server_FTP/repo/lib/net/minecraftforge/forgespi/7.0.1/forgespi-7.0.1.jar"
              }
            },
            {
              "id": "net.minecraftforge:coremods:5.2.4",
              "name": "Minecraft Forge (coremods)",
              "type": "Library",
              "artifact": {
                "size": 31872,
                "MD5": "5295505357ba9b98450c5e3121f82191",
                "url": "https://awe4859.github.io/moon_server_FTP/repo/lib/net/minecraftforge/coremods/5.2.4/coremods-5.2.4.jar"
              }
            },
            {
              "id": "cpw.mods:modlauncher:10.0.9",
              "name": "Minecraft Forge (modlauncher)",
              "type": "Library",
              "artifact": {
                "size": 130343,
                "MD5": "07507d18d72661f8ae6a5da75bbf35be",
                "url": "https://awe4859.github.io/moon_server_FTP/repo/lib/cpw/mods/modlauncher/10.0.9/modlauncher-10.0.9.jar"
              }
            },
            {
              "id": "net.minecraftforge:unsafe:0.2.0",
              "name": "Minecraft Forge (unsafe)",
              "type": "Library",
              "artifact": {
                "size": 2834,
                "MD5": "2d1016ebe4c1a63dd50a59d26bd12db1",
                "url": "https://awe4859.github.io/moon_server_FTP/repo/lib/net/minecraftforge/unsafe/0.2.0/unsafe-0.2.0.jar"
              }
            },
            {
              "id": "net.minecraftforge:mergetool:1.1.5:api",
              "name": "Minecraft Forge (mergetool)",
              "type": "Library",
              "artifact": {
                "size": 2572,
                "MD5": "8df9c5bf87d004ddb884eca99bc2a4b1",
                "url": "https://awe4859.github.io/moon_server_FTP/repo/lib/net/minecraftforge/mergetool/1.1.5/mergetool-1.1.5-api.jar"
              }
            },
            {
              "id": "com.electronwill.night-config:core:3.6.4",
              "name": "Minecraft Forge (core)",
              "type": "Library",
              "artifact": {
                "size": 199834,
                "MD5": "d83ab07267e402131fb93d899a57f5cd",
                "url": "https://awe4859.github.io/moon_server_FTP/repo/lib/com/electronwill/night-config/core/3.6.4/core-3.6.4.jar"
              }
            },
            {
              "id": "com.electronwill.night-config:toml:3.6.4",
              "name": "Minecraft Forge (toml)",
              "type": "Library",
              "artifact": {
                "size": 31816,
                "MD5": "bc95d0709fff2164b01fd09fbc988be8",
                "url": "https://awe4859.github.io/moon_server_FTP/repo/lib/com/electronwill/night-config/toml/3.6.4/toml-3.6.4.jar"
              }
            },
            {
              "id": "org.apache.maven:maven-artifact:3.8.5",
              "name": "Minecraft Forge (maven-artifact)",
              "type": "Library",
              "artifact": {
                "size": 58077,
                "MD5": "ce473b0d9fbfd10fe147f03fe8707d67",
                "url": "https://awe4859.github.io/moon_server_FTP/repo/lib/org/apache/maven/maven-artifact/3.8.5/maven-artifact-3.8.5.jar"
              }
            },
            {
              "id": "net.jodah:typetools:0.6.3",
              "name": "Minecraft Forge (typetools)",
              "type": "Library",
              "artifact": {
                "size": 18281,
                "MD5": "d4a375bf382f726cf1a650ccb38a736c",
                "url": "https://awe4859.github.io/moon_server_FTP/repo/lib/net/jodah/typetools/0.6.3/typetools-0.6.3.jar"
              }
            },
            {
              "id": "net.minecrell:terminalconsoleappender:1.2.0",
              "name": "Minecraft Forge (terminalconsoleappender)",
              "type": "Library",
              "artifact": {
                "size": 15977,
                "MD5": "679363fa893293791e55a21f81342f87",
                "url": "https://awe4859.github.io/moon_server_FTP/repo/lib/net/minecrell/terminalconsoleappender/1.2.0/terminalconsoleappender-1.2.0.jar"
              }
            },
            {
              "id": "org.jline:jline-reader:3.12.1",
              "name": "Minecraft Forge (jline-reader)",
              "type": "Library",
              "artifact": {
                "size": 150765,
                "MD5": "a2e7b012cd9802f83321187409174a94",
                "url": "https://awe4859.github.io/moon_server_FTP/repo/lib/org/jline/jline-reader/3.12.1/jline-reader-3.12.1.jar"
              }
            },
            {
              "id": "org.jline:jline-terminal:3.12.1",
              "name": "Minecraft Forge (jline-terminal)",
              "type": "Library",
              "artifact": {
                "size": 211712,
                "MD5": "3c52be5ab5e3847be6e62269de924cb0",
                "url": "https://awe4859.github.io/moon_server_FTP/repo/lib/org/jline/jline-terminal/3.12.1/jline-terminal-3.12.1.jar"
              }
            },
            {
              "id": "org.spongepowered:mixin:0.8.5",
              "name": "Minecraft Forge (mixin)",
              "type": "Library",
              "artifact": {
                "size": 1089277,
                "MD5": "19b3a2ae9e445a6e626fd7d1648cfcb8",
                "url": "https://awe4859.github.io/moon_server_FTP/repo/lib/org/spongepowered/mixin/0.8.5/mixin-0.8.5.jar"
              }
            },
            {
              "id": "org.openjdk.nashorn:nashorn-core:15.4",
              "name": "Minecraft Forge (nashorn-core)",
              "type": "Library",
              "artifact": {
                "size": 2167292,
                "MD5": "a9b3360e6a486cf62c1952c7816b7d97",
                "url": "https://awe4859.github.io/moon_server_FTP/repo/lib/org/openjdk/nashorn/nashorn-core/15.4/nashorn-core-15.4.jar"
              }
            },
            {
              "id": "net.minecraftforge:JarJarSelector:0.3.19",
              "name": "Minecraft Forge (JarJarSelector)",
              "type": "Library",
              "artifact": {
                "size": 17374,
                "MD5": "2bb6cbe0e6c6fbcd8f92d2e6b1ea678e",
                "url": "https://awe4859.github.io/moon_server_FTP/repo/lib/net/minecraftforge/JarJarSelector/0.3.19/JarJarSelector-0.3.19.jar"
              }
            },
            {
              "id": "net.minecraftforge:JarJarMetadata:0.3.19",
              "name": "Minecraft Forge (JarJarMetadata)",
              "type": "Library",
              "artifact": {
                "size": 15895,
                "MD5": "9633546d299d4282ca68d10582be1c8f",
                "url": "https://awe4859.github.io/moon_server_FTP/repo/lib/net/minecraftforge/JarJarMetadata/0.3.19/JarJarMetadata-0.3.19.jar"
              }
            },
            {
              "id": "cpw.mods:bootstraplauncher:1.1.2",
              "name": "Minecraft Forge (bootstraplauncher)",
              "type": "Library",
              "artifact": {
                "size": 8284,
                "MD5": "48f5255aa337344c467c0150d347813d",
                "url": "https://awe4859.github.io/moon_server_FTP/repo/lib/cpw/mods/bootstraplauncher/1.1.2/bootstraplauncher-1.1.2.jar"
              }
            },
            {
              "id": "net.minecraftforge:JarJarFileSystems:0.3.19",
              "name": "Minecraft Forge (JarJarFileSystems)",
              "type": "Library",
              "artifact": {
                "size": 32195,
                "MD5": "c2be1a88b63eb1b58b00ab6e498cd97d",
                "url": "https://awe4859.github.io/moon_server_FTP/repo/lib/net/minecraftforge/JarJarFileSystems/0.3.19/JarJarFileSystems-0.3.19.jar"
              }
            },
            {
              "id": "net.minecraftforge:fmlloader:1.20.1-47.3.22",
              "name": "Minecraft Forge (fmlloader)",
              "type": "Library",
              "artifact": {
                "size": 265988,
                "MD5": "78a50d4f473dead4d2f7464c48b115f6",
                "url": "https://awe4859.github.io/moon_server_FTP/repo/lib/net/minecraftforge/fmlloader/1.20.1-47.3.22/fmlloader-1.20.1-47.3.22.jar"
              }
            },
            {
              "id": "net.minecraftforge:fmlearlydisplay:1.20.1-47.3.22",
              "name": "Minecraft Forge (fmlearlydisplay)",
              "type": "Library",
              "artifact": {
                "size": 170460,
                "MD5": "7cfddfbe25d1b46170b2e3850c91f03d",
                "url": "https://awe4859.github.io/moon_server_FTP/repo/lib/net/minecraftforge/fmlearlydisplay/1.20.1-47.3.22/fmlearlydisplay-1.20.1-47.3.22.jar"
              }
            }
          ]
        },
        {
          "id": "com.ncpbails:alexsdelight:1.5@jar",
          "name": "Alex's Delight",
          "type": "ForgeMod",
          "artifact": {
            "size": 55398,
            "url": "https://awe4859.github.io/moon_server_FTP/servers/%EB%A3%A8%EB%82%98%ED%83%80%EC%9A%B4-1.20.1/forgemods/required/alexsdelight-1.5.jar",
            "MD5": "b969e136e1f9a70c42dd102ed8359b40"
          }
        },
        {
          "id": "squeek.appleskin:appleskin:2.5.1+mc1.20.1@jar",
          "name": "AppleSkin",
          "type": "ForgeMod",
          "artifact": {
            "size": 47428,
            "url": "https://awe4859.github.io/moon_server_FTP/servers/%EB%A3%A8%EB%82%98%ED%83%80%EC%9A%B4-1.20.1/forgemods/required/appleskin-forge-mc1.20.1-2.5.1.jar",
            "MD5": "dae63cea9c951dda542a4005ceef3953"
          }
        },
        {
          "id": "net.blay09.mods:balm:7.3.10@jar",
          "name": "Balm",
          "type": "ForgeMod",
          "artifact": {
            "size": 373791,
            "url": "https://awe4859.github.io/moon_server_FTP/servers/%EB%A3%A8%EB%82%98%ED%83%80%EC%9A%B4-1.20.1/forgemods/required/balm-forge-1.20.1-7.3.10-all.jar",
            "MD5": "53ab1e5640e1378bac5a933b05519f9a"
          }
        },
        {
          "id": "com.vladmarica:betterpingdisplay:1.1@jar",
          "name": "Better Ping Display",
          "type": "ForgeMod",
          "artifact": {
            "size": 15889,
            "url": "https://awe4859.github.io/moon_server_FTP/servers/%EB%A3%A8%EB%82%98%ED%83%80%EC%9A%B4-1.20.1/forgemods/required/BetterPingDisplay-1.20.1-1.1.jar",
            "MD5": "2a331e8f5a7cc2609d67f7975fba7d7e"
          }
        },
        {
          "id": "com.mrcrayfish.furniture:cfm:7.0.0-pre36@jar",
          "name": "MrCrayfish's Furniture Mod",
          "type": "ForgeMod",
          "artifact": {
            "size": 2613393,
            "url": "https://awe4859.github.io/moon_server_FTP/servers/%EB%A3%A8%EB%82%98%ED%83%80%EC%9A%B4-1.20.1/forgemods/required/cfm-forge-1.20.1-7.0.0-pre36.jar",
            "MD5": "faf78627dad9c9c04e7a4fa8992c54dc"
          }
        },
        {
          "id": "net.blay09.mods:cookingforblockheads:16.0.9@jar",
          "name": "CookingForBlockheads",
          "type": "ForgeMod",
          "artifact": {
            "size": 815694,
            "url": "https://awe4859.github.io/moon_server_FTP/servers/%EB%A3%A8%EB%82%98%ED%83%80%EC%9A%B4-1.20.1/forgemods/required/cookingforblockheads-forge-1.20.1-16.0.9.jar",
            "MD5": "48b7824fc141e3f7ee26459a445193dd"
          }
        },
        {
          "id": "com.blamejared:crafttweaker:14.0.56@jar",
          "name": "CraftTweaker",
          "type": "ForgeMod",
          "artifact": {
            "size": 3263879,
            "url": "https://awe4859.github.io/moon_server_FTP/servers/%EB%A3%A8%EB%82%98%ED%83%80%EC%9A%B4-1.20.1/forgemods/required/CraftTweaker-forge-1.20.1-14.0.56.jar",
            "MD5": "f4dbb9a7daa5f04919c0a410dfd92d37"
          }
        },
        {
          "id": "com.epherical:croptopia:3.0.4@jar",
          "name": "Croptopia",
          "type": "ForgeMod",
          "artifact": {
            "size": 2099945,
            "url": "https://awe4859.github.io/moon_server_FTP/servers/%EB%A3%A8%EB%82%98%ED%83%80%EC%9A%B4-1.20.1/forgemods/required/Croptopia-1.20.1-FORGE-3.0.4.jar",
            "MD5": "c7c4e6f0ff51507ad64544991dfc7454"
          }
        },
        {
          "id": "net.yablon.decorativestorage:decorative_storage:2.1212@jar",
          "name": "Decorative Storage",
          "type": "ForgeMod",
          "artifact": {
            "size": 613691,
            "url": "https://awe4859.github.io/moon_server_FTP/servers/%EB%A3%A8%EB%82%98%ED%83%80%EC%9A%B4-1.20.1/forgemods/required/decorative_storage-2.1212-forge-1.20.1.jar",
            "MD5": "c3080fac79448f6338aa85a441664a9c"
          }
        },
        {
          "id": "me.jellysquid.mods.sodium.client:embeddium:0.3.31+mc1.20.1@jar",
          "name": "Embeddium",
          "type": "ForgeMod",
          "artifact": {
            "size": 1320675,
            "url": "https://awe4859.github.io/moon_server_FTP/servers/%EB%A3%A8%EB%82%98%ED%83%80%EC%9A%B4-1.20.1/forgemods/required/embeddium-0.3.31+mc1.20.1.jar",
            "MD5": "1dfb2ee49ce9ad5d484ff3eea0d628b7"
          }
        },
        {
          "id": "com.epherical:epherolib:0.1.2@jar",
          "name": "BOZOID",
          "type": "ForgeMod",
          "artifact": {
            "size": 756864,
            "url": "https://awe4859.github.io/moon_server_FTP/servers/%EB%A3%A8%EB%82%98%ED%83%80%EC%9A%B4-1.20.1/forgemods/required/EpheroLib-1.20.1-FORGE-1.2.0.jar",
            "MD5": "f8b4d202f3fc4ffaf1bb8efd79f860bd"
          }
        },
        {
          "id": "vectorwing.farmersdelight:farmersdelight:1.20.1-1.2.6@jar",
          "name": "Farmer's Delight",
          "type": "ForgeMod",
          "artifact": {
            "size": 2944818,
            "url": "https://awe4859.github.io/moon_server_FTP/servers/%EB%A3%A8%EB%82%98%ED%83%80%EC%9A%B4-1.20.1/forgemods/required/FarmersDelight-1.20.1-1.2.6.jar",
            "MD5": "3bedf3198980957b909a2ce41557960d"
          }
        },
        {
          "id": "malte0811.ferritecore:ferritecore:6.0.1@jar",
          "name": "Ferrite Core",
          "type": "ForgeMod",
          "artifact": {
            "size": 123034,
            "url": "https://awe4859.github.io/moon_server_FTP/servers/%EB%A3%A8%EB%82%98%ED%83%80%EC%9A%B4-1.20.1/forgemods/required/ferritecore-6.0.1-forge.jar",
            "MD5": "f52f538207a4829d7060550092ce2383"
          }
        },
        {
          "id": "mezz.jei:jei:15.20.0.106@jar",
          "name": "Just Enough Items",
          "type": "ForgeMod",
          "artifact": {
            "size": 1379220,
            "url": "https://awe4859.github.io/moon_server_FTP/servers/%EB%A3%A8%EB%82%98%ED%83%80%EC%9A%B4-1.20.1/forgemods/required/jei-1.20.1-forge-15.20.0.106.jar",
            "MD5": "245af433575aef3a47ae73492196018f"
          }
        },
        {
          "id": "journeymap:journeymap:5.10.3@jar",
          "name": "Journeymap",
          "type": "ForgeMod",
          "artifact": {
            "size": 7160405,
            "url": "https://awe4859.github.io/moon_server_FTP/servers/%EB%A3%A8%EB%82%98%ED%83%80%EC%9A%B4-1.20.1/forgemods/required/journeymap-1.20.1-5.10.3-forge.jar",
            "MD5": "2181bd6b7161f06726560b9382235611"
          }
        },
        {
          "id": "com.hyfata.najoan.koreanpatch.client:koreanpatch:1.6.11+mc1.20.1@jar",
          "name": "Korean Patch",
          "type": "ForgeMod",
          "artifact": {
            "size": 194923,
            "url": "https://awe4859.github.io/moon_server_FTP/servers/%EB%A3%A8%EB%82%98%ED%83%80%EC%9A%B4-1.20.1/forgemods/required/koreanpatch-forge-1.6.11+mc1.20.1.jar",
            "MD5": "f3f44f46e991ce19fad6080231335d52"
          }
        },
        {
          "id": "com.mcwfences.kikoz:mcwfences:1.1.2@jar",
          "name": "Macaw's Fences and Walls",
          "type": "ForgeMod",
          "artifact": {
            "size": 522886,
            "url": "https://awe4859.github.io/moon_server_FTP/servers/%EB%A3%A8%EB%82%98%ED%83%80%EC%9A%B4-1.20.1/forgemods/required/mcw-fences-1.1.2-mc1.20.1forge.jar",
            "MD5": "729a8ce749bb6deff288ea1791ff9602"
          }
        },
        {
          "id": "com.mcwlights.kikoz:mcwlights:1.1.0@jar",
          "name": "Macaw's Lights and Lamps",
          "type": "ForgeMod",
          "artifact": {
            "size": 517513,
            "url": "https://awe4859.github.io/moon_server_FTP/servers/%EB%A3%A8%EB%82%98%ED%83%80%EC%9A%B4-1.20.1/forgemods/required/mcw-lights-1.1.0-mc1.20.1forge.jar",
            "MD5": "539aa2ab27253c1053236e06b82374df"
          }
        },
        {
          "id": "ca.fxco:memoryleakfix:1.1.5@jar",
          "name": "Memory Leak Fix",
          "type": "ForgeMod",
          "artifact": {
            "size": 227925,
            "url": "https://awe4859.github.io/moon_server_FTP/servers/%EB%A3%A8%EB%82%98%ED%83%80%EC%9A%B4-1.20.1/forgemods/required/memoryleakfix-forge-1.17+-1.1.5.jar",
            "MD5": "5dd9149414ca375ceab146242c6e84ab"
          }
        },
        {
          "id": "com.axperty:moredelight:24.11.06-1.20-forge@jar",
          "name": "More Delight",
          "type": "ForgeMod",
          "artifact": {
            "size": 137983,
            "url": "https://awe4859.github.io/moon_server_FTP/servers/%EB%A3%A8%EB%82%98%ED%83%80%EC%9A%B4-1.20.1/forgemods/required/moredelight-24.11.06-1.20-forge.jar",
            "MD5": "7c4bcef1dc59e184e01209298c8043af"
          }
        },
        {
          "id": "yalter.mousetweaks:mousetweaks:2.25.1@jar",
          "name": "Mouse Tweaks",
          "type": "ForgeMod",
          "artifact": {
            "size": 76237,
            "url": "https://awe4859.github.io/moon_server_FTP/servers/%EB%A3%A8%EB%82%98%ED%83%80%EC%9A%B4-1.20.1/forgemods/required/MouseTweaks-forge-mc1.20.1-2.25.1.jar",
            "MD5": "ce4b5bbb9ef6a7905c458ab599ef4cb2"
          }
        },
        {
          "id": "net.irisshaders.iris:oculus:1.8.0@jar",
          "name": "Oculus",
          "type": "ForgeMod",
          "artifact": {
            "size": 2851119,
            "url": "https://awe4859.github.io/moon_server_FTP/servers/%EB%A3%A8%EB%82%98%ED%83%80%EC%9A%B4-1.20.1/forgemods/required/oculus-mc1.20.1-1.8.0.jar",
            "MD5": "1dd891634ac21591b5a692471f112572"
          }
        },
        {
          "id": "com.matyrobbrt:okzoomer:3.0.1@jar",
          "name": "OkZoomer",
          "type": "ForgeMod",
          "artifact": {
            "size": 120046,
            "url": "https://awe4859.github.io/moon_server_FTP/servers/%EB%A3%A8%EB%82%98%ED%83%80%EC%9A%B4-1.20.1/forgemods/required/okzoomer-forge-1.20-3.0.1.jar",
            "MD5": "cae64657bac994d5d116ef25b5978913"
          }
        },
        {
          "id": "net.orcinus.overweightfarming:overweight_farming:1.20.1-2.1.0-forge@jar",
          "name": "Overweight Farming",
          "type": "ForgeMod",
          "artifact": {
            "size": 268241,
            "url": "https://awe4859.github.io/moon_server_FTP/servers/%EB%A3%A8%EB%82%98%ED%83%80%EC%9A%B4-1.20.1/forgemods/required/overweightfarming-1.20.1-2.1.0-forge.jar",
            "MD5": "06478991ae296d15078384372446b785"
          }
        },
        {
          "id": "io.github.jamalam360:rightclickharvest:3.2.0+1.20.1-forge@jar",
          "name": "Right Click Harvest",
          "type": "ForgeMod",
          "artifact": {
            "size": 265052,
            "url": "https://awe4859.github.io/moon_server_FTP/servers/%EB%A3%A8%EB%82%98%ED%83%80%EC%9A%B4-1.20.1/forgemods/required/right-click-harvest-3.2.0+1.20.1-forge.jar",
            "MD5": "23f4521a42c0f2e950919f3abeab2243"
          }
        },
        {
          "id": "com.abdelaziz:smoothboot:0.0.4@jar",
          "name": "Smooth Boot (Reloaded)",
          "type": "ForgeMod",
          "artifact": {
            "size": 41044,
            "url": "https://awe4859.github.io/moon_server_FTP/servers/%EB%A3%A8%EB%82%98%ED%83%80%EC%9A%B4-1.20.1/forgemods/required/smoothboot(reloaded)-mc1.20.1-0.0.4.jar",
            "MD5": "c8cd5ae14d99796fd92c95a353e96211"
          }
        },
        {
          "id": "default.json",
          "name": "default.json",
          "type": "File",
          "artifact": {
            "size": 623,
            "url": "https://awe4859.github.io/moon_server_FTP/servers/%EB%A3%A8%EB%82%98%ED%83%80%EC%9A%B4-1.20.1/files/resourcepacks/%EB%A3%A8%EB%82%98%ED%83%80%EC%9A%B4/assets/minecraft/font/default.json",
            "MD5": "9d0e0b90696f7af6960e8ba4c359178c",
            "path": "resourcepacks/루나타운/assets/minecraft/font/default.json"
          }
        },
        {
          "id": "bronzebungeoppang.json",
          "name": "bronzebungeoppang.json",
          "type": "File",
          "artifact": {
            "size": 119,
            "url": "https://awe4859.github.io/moon_server_FTP/servers/%EB%A3%A8%EB%82%98%ED%83%80%EC%9A%B4-1.20.1/files/resourcepacks/%EB%A3%A8%EB%82%98%ED%83%80%EC%9A%B4/assets/minecraft/models/custom/bronzebungeoppang.json",
            "MD5": "ca0c7c8f0e63454421be9e71de7f83bc",
            "path": "resourcepacks/루나타운/assets/minecraft/models/custom/bronzebungeoppang.json"
          }
        },
        {
          "id": "glodbungeoppang.json",
          "name": "glodbungeoppang.json",
          "type": "File",
          "artifact": {
            "size": 117,
            "url": "https://awe4859.github.io/moon_server_FTP/servers/%EB%A3%A8%EB%82%98%ED%83%80%EC%9A%B4-1.20.1/files/resourcepacks/%EB%A3%A8%EB%82%98%ED%83%80%EC%9A%B4/assets/minecraft/models/custom/glodbungeoppang.json",
            "MD5": "4d1cd73f54367f2e80326dd97a589fc9",
            "path": "resourcepacks/루나타운/assets/minecraft/models/custom/glodbungeoppang.json"
          }
        },
        {
          "id": "none.json",
          "name": "none.json",
          "type": "File",
          "artifact": {
            "size": 106,
            "url": "https://awe4859.github.io/moon_server_FTP/servers/%EB%A3%A8%EB%82%98%ED%83%80%EC%9A%B4-1.20.1/files/resourcepacks/%EB%A3%A8%EB%82%98%ED%83%80%EC%9A%B4/assets/minecraft/models/custom/none.json",
            "MD5": "a949f6f548cb528252921f589d39d225",
            "path": "resourcepacks/루나타운/assets/minecraft/models/custom/none.json"
          }
        },
        {
          "id": "silverbungeoppang.json",
          "name": "silverbungeoppang.json",
          "type": "File",
          "artifact": {
            "size": 119,
            "url": "https://awe4859.github.io/moon_server_FTP/servers/%EB%A3%A8%EB%82%98%ED%83%80%EC%9A%B4-1.20.1/files/resourcepacks/%EB%A3%A8%EB%82%98%ED%83%80%EC%9A%B4/assets/minecraft/models/custom/silverbungeoppang.json",
            "MD5": "ba8ce7f992f945158c9ce4df29d42371",
            "path": "resourcepacks/루나타운/assets/minecraft/models/custom/silverbungeoppang.json"
          }
        },
        {
          "id": "glass_pane.json",
          "name": "glass_pane.json",
          "type": "File",
          "artifact": {
            "size": 226,
            "url": "https://awe4859.github.io/moon_server_FTP/servers/%EB%A3%A8%EB%82%98%ED%83%80%EC%9A%B4-1.20.1/files/resourcepacks/%EB%A3%A8%EB%82%98%ED%83%80%EC%9A%B4/assets/minecraft/models/item/glass_pane.json",
            "MD5": "fe9706fa3887e1a36e6323080566d765",
            "path": "resourcepacks/루나타운/assets/minecraft/models/item/glass_pane.json"
          }
        },
        {
          "id": "paper.json",
          "name": "paper.json",
          "type": "File",
          "artifact": {
            "size": 426,
            "url": "https://awe4859.github.io/moon_server_FTP/servers/%EB%A3%A8%EB%82%98%ED%83%80%EC%9A%B4-1.20.1/files/resourcepacks/%EB%A3%A8%EB%82%98%ED%83%80%EC%9A%B4/assets/minecraft/models/item/paper.json",
            "MD5": "e2c597946524c9262114d96f73053e80",
            "path": "resourcepacks/루나타운/assets/minecraft/models/item/paper.json"
          }
        },
        {
          "id": "menu.png",
          "name": "menu.png",
          "type": "File",
          "artifact": {
            "size": 25875,
            "url": "https://awe4859.github.io/moon_server_FTP/servers/%EB%A3%A8%EB%82%98%ED%83%80%EC%9A%B4-1.20.1/files/resourcepacks/%EB%A3%A8%EB%82%98%ED%83%80%EC%9A%B4/assets/minecraft/textures/font/menu.png",
            "MD5": "d339aecb96b13994edf7f734178dc97e",
            "path": "resourcepacks/루나타운/assets/minecraft/textures/font/menu.png"
          }
        },
        {
          "id": "op.png",
          "name": "op.png",
          "type": "File",
          "artifact": {
            "size": 5753,
            "url": "https://awe4859.github.io/moon_server_FTP/servers/%EB%A3%A8%EB%82%98%ED%83%80%EC%9A%B4-1.20.1/files/resourcepacks/%EB%A3%A8%EB%82%98%ED%83%80%EC%9A%B4/assets/minecraft/textures/font/op.png",
            "MD5": "dff1cf19b986be543c6a2bfdc267a083",
            "path": "resourcepacks/루나타운/assets/minecraft/textures/font/op.png"
          }
        },
        {
          "id": "player.png",
          "name": "player.png",
          "type": "File",
          "artifact": {
            "size": 24238,
            "url": "https://awe4859.github.io/moon_server_FTP/servers/%EB%A3%A8%EB%82%98%ED%83%80%EC%9A%B4-1.20.1/files/resourcepacks/%EB%A3%A8%EB%82%98%ED%83%80%EC%9A%B4/assets/minecraft/textures/font/player.png",
            "MD5": "265ef5f738d6c0dadf1404850fee7a28",
            "path": "resourcepacks/루나타운/assets/minecraft/textures/font/player.png"
          }
        },
        {
          "id": "space.png",
          "name": "space.png",
          "type": "File",
          "artifact": {
            "size": 868,
            "url": "https://awe4859.github.io/moon_server_FTP/servers/%EB%A3%A8%EB%82%98%ED%83%80%EC%9A%B4-1.20.1/files/resourcepacks/%EB%A3%A8%EB%82%98%ED%83%80%EC%9A%B4/assets/minecraft/textures/font/space.png",
            "MD5": "d2c3d5015bd51b58dcd8c96b4766e169",
            "path": "resourcepacks/루나타운/assets/minecraft/textures/font/space.png"
          }
        },
        {
          "id": "bronzebungeoppang.png",
          "name": "bronzebungeoppang.png",
          "type": "File",
          "artifact": {
            "size": 26167,
            "url": "https://awe4859.github.io/moon_server_FTP/servers/%EB%A3%A8%EB%82%98%ED%83%80%EC%9A%B4-1.20.1/files/resourcepacks/%EB%A3%A8%EB%82%98%ED%83%80%EC%9A%B4/assets/minecraft/textures/item/bronzebungeoppang.png",
            "MD5": "3c64f302908386cfd3a941964c0a36fc",
            "path": "resourcepacks/루나타운/assets/minecraft/textures/item/bronzebungeoppang.png"
          }
        },
        {
          "id": "glodbungeoppang.png",
          "name": "glodbungeoppang.png",
          "type": "File",
          "artifact": {
            "size": 25514,
            "url": "https://awe4859.github.io/moon_server_FTP/servers/%EB%A3%A8%EB%82%98%ED%83%80%EC%9A%B4-1.20.1/files/resourcepacks/%EB%A3%A8%EB%82%98%ED%83%80%EC%9A%B4/assets/minecraft/textures/item/glodbungeoppang.png",
            "MD5": "bddf28de0a4b860d197869178fd3c4bc",
            "path": "resourcepacks/루나타운/assets/minecraft/textures/item/glodbungeoppang.png"
          }
        },
        {
          "id": "none.png",
          "name": "none.png",
          "type": "File",
          "artifact": {
            "size": 81,
            "url": "https://awe4859.github.io/moon_server_FTP/servers/%EB%A3%A8%EB%82%98%ED%83%80%EC%9A%B4-1.20.1/files/resourcepacks/%EB%A3%A8%EB%82%98%ED%83%80%EC%9A%B4/assets/minecraft/textures/item/none.png",
            "MD5": "488cb0b25cbcc3b4003f2f0fe70d673c",
            "path": "resourcepacks/루나타운/assets/minecraft/textures/item/none.png"
          }
        },
        {
          "id": "paper.png",
          "name": "paper.png",
          "type": "File",
          "artifact": {
            "size": 176,
            "url": "https://awe4859.github.io/moon_server_FTP/servers/%EB%A3%A8%EB%82%98%ED%83%80%EC%9A%B4-1.20.1/files/resourcepacks/%EB%A3%A8%EB%82%98%ED%83%80%EC%9A%B4/assets/minecraft/textures/item/paper.png",
            "MD5": "041ad9ebb48ef7754bca5dd4422a02ab",
            "path": "resourcepacks/루나타운/assets/minecraft/textures/item/paper.png"
          }
        },
        {
          "id": "silverbungeoppang.png",
          "name": "silverbungeoppang.png",
          "type": "File",
          "artifact": {
            "size": 20985,
            "url": "https://awe4859.github.io/moon_server_FTP/servers/%EB%A3%A8%EB%82%98%ED%83%80%EC%9A%B4-1.20.1/files/resourcepacks/%EB%A3%A8%EB%82%98%ED%83%80%EC%9A%B4/assets/minecraft/textures/item/silverbungeoppang.png",
            "MD5": "35984a18a748ba610fba4bac14621002",
            "path": "resourcepacks/루나타운/assets/minecraft/textures/item/silverbungeoppang.png"
          }
        },
        {
          "id": "pack.mcmeta",
          "name": "pack.mcmeta",
          "type": "File",
          "artifact": {
            "size": 220,
            "url": "https://awe4859.github.io/moon_server_FTP/servers/%EB%A3%A8%EB%82%98%ED%83%80%EC%9A%B4-1.20.1/files/resourcepacks/%EB%A3%A8%EB%82%98%ED%83%80%EC%9A%B4/pack.mcmeta",
            "MD5": "7c3ac2efe926ff25182dc66caeecd577",
            "path": "resourcepacks/루나타운/pack.mcmeta"
          }
        },
        {
          "id": "pack.png",
          "name": "pack.png",
          "type": "File",
          "artifact": {
            "size": 23448,
            "url": "https://awe4859.github.io/moon_server_FTP/servers/%EB%A3%A8%EB%82%98%ED%83%80%EC%9A%B4-1.20.1/files/resourcepacks/%EB%A3%A8%EB%82%98%ED%83%80%EC%9A%B4/pack.png",
            "MD5": "a56f441852b206b2edb26e85795874b5",
            "path": "resourcepacks/루나타운/pack.png"
          }
        },
        {
          "id": "Bliss_v2.0.4_(Chocapic13_Shaders_edit).zip",
          "name": "Bliss_v2.0.4_(Chocapic13_Shaders_edit).zip",
          "type": "File",
          "artifact": {
            "size": 1669167,
            "url": "https://awe4859.github.io/moon_server_FTP/servers/%EB%A3%A8%EB%82%98%ED%83%80%EC%9A%B4-1.20.1/files/shaderpacks/Bliss_v2.0.4_(Chocapic13_Shaders_edit).zip",
            "MD5": "fb757db17e378d3174611d4d0698280d",
            "path": "shaderpacks/Bliss_v2.0.4_(Chocapic13_Shaders_edit).zip"
          }
        },
        {
          "id": "BSL_v8.4.zip",
          "name": "BSL_v8.4.zip",
          "type": "File",
          "artifact": {
            "size": 1105442,
            "url": "https://awe4859.github.io/moon_server_FTP/servers/%EB%A3%A8%EB%82%98%ED%83%80%EC%9A%B4-1.20.1/files/shaderpacks/BSL_v8.4.zip",
            "MD5": "9cbe8c2b70a992a50853875482eec66a",
            "path": "shaderpacks/BSL_v8.4.zip"
          }
        },
        {
          "id": "ComplementaryReimagined_r5.4.zip",
          "name": "ComplementaryReimagined_r5.4.zip",
          "type": "File",
          "artifact": {
            "size": 452405,
            "url": "https://awe4859.github.io/moon_server_FTP/servers/%EB%A3%A8%EB%82%98%ED%83%80%EC%9A%B4-1.20.1/files/shaderpacks/ComplementaryReimagined_r5.4.zip",
            "MD5": "1a67030845ad123f56a3b5f6d8fb9b7c",
            "path": "shaderpacks/ComplementaryReimagined_r5.4.zip"
          }
        },
        {
          "id": "ComplementaryUnbound_r5.4.zip",
          "name": "ComplementaryUnbound_r5.4.zip",
          "type": "File",
          "artifact": {
            "size": 452408,
            "url": "https://awe4859.github.io/moon_server_FTP/servers/%EB%A3%A8%EB%82%98%ED%83%80%EC%9A%B4-1.20.1/files/shaderpacks/ComplementaryUnbound_r5.4.zip",
            "MD5": "94f56d5c5c343b9a0f4ad7eb135f9afa",
            "path": "shaderpacks/ComplementaryUnbound_r5.4.zip"
          }
        },
        {
          "id": "Kappa_v5.2.zip",
          "name": "Kappa_v5.2.zip",
          "type": "File",
          "artifact": {
            "size": 3868665,
            "url": "https://awe4859.github.io/moon_server_FTP/servers/%EB%A3%A8%EB%82%98%ED%83%80%EC%9A%B4-1.20.1/files/shaderpacks/Kappa_v5.2.zip",
            "MD5": "70033041456689e15ea1d521016ebb35",
            "path": "shaderpacks/Kappa_v5.2.zip"
          }
        },
        {
          "id": "Sildur's Vibrant Shaders v1.52 Extreme-VL.zip",
          "name": "Sildur's Vibrant Shaders v1.52 Extreme-VL.zip",
          "type": "File",
          "artifact": {
            "size": 142504,
            "url": "https://awe4859.github.io/moon_server_FTP/servers/%EB%A3%A8%EB%82%98%ED%83%80%EC%9A%B4-1.20.1/files/shaderpacks/Sildur's%20Vibrant%20Shaders%20v1.52%20Extreme-VL.zip",
            "MD5": "82a198c41b07f33a7ebb1b9d27ada3f0",
            "path": "shaderpacks/Sildur's Vibrant Shaders v1.52 Extreme-VL.zip"
          }
        }
      ]
    }
  ]
}